CHANGELOG.md
sanic_openapi_ext/__init__.py
sanic_openapi_ext/marshmallow.py
sanic_openapi_ext-0.1.0.dist-info/LICENSE
sanic_openapi_ext-0.1.0.dist-info/METADATA
sanic_openapi_ext-0.1.0.dist-info/WHEEL
sanic_openapi_ext-0.1.0.dist-info/RECORD
