Metadata-Version: 2.1
Name: sanic-openapi-ext
Version: 0.1.0
Summary: Sanic OpenAPI extension offers an enhanced and convenient way to generate OpenAPI (Swagger) documentation from Marshmallow schemas
Home-page: https://pypi.org/project/sanic-openapi-ext/
License: MIT
Keywords: python,sanic,swagger,marshmallow,open-api,sanic-ext
Author: Yurii Havrylko
Author-email: yurii.havrylko@gmail.com
Requires-Python: >=3.8,<4.0
Classifier: Development Status :: 3 - Alpha
Classifier: Intended Audience :: Developers
Classifier: License :: OSI Approved :: MIT License
Classifier: Operating System :: OS Independent
Classifier: Programming Language :: Python :: 3
Classifier: Programming Language :: Python :: 3.8
Classifier: Programming Language :: Python :: 3.9
Classifier: Programming Language :: Python :: 3.10
Classifier: Programming Language :: Python :: 3.11
Classifier: Programming Language :: Python :: 3.12
Classifier: Topic :: Software Development :: Libraries :: Python Modules
Requires-Dist: marshmallow (>=3.20.2,<4.0.0)
Requires-Dist: sanic-ext (>=23.12.0,<24.0.0)
Project-URL: Documentation, https://github.com/yuriihavrylko/sanic_openapi_ext/blob/master/README.md
Project-URL: Repository, https://github.com/yuriihavrylko/sanic_openapi_ext
